{
  "version": "7",
  "dialect": "postgresql",
  "entries": [
    {
      "idx": 0,
      "version": "7",
      "when": 1726873858475,
      "tag": "0000_misty_scourge",
      "breakpoints": true
    },
    {
      "idx": 1,
      "version": "7",
      "when": 1726874095254,
      "tag": "0001_faithful_trish_tilby",
      "breakpoints": true
    },
    {
      "idx": 2,
      "version": "7",
      "when": 1726874363698,
      "tag": "0002_slim_fallen_one",
      "breakpoints": true
    },
    {
      "idx": 3,
      "version": "7",
      "when": 1726874520851,
      "tag": "0003_closed_masque",
      "breakpoints": true
    },
    {
      "idx": 4,
      "version": "7",
      "when": 1726930370607,
      "tag": "0004_flat_silver_fox",
      "breakpoints": true
    },
    {
      "idx": 5,
      "version": "7",
      "when": 1727219163571,
      "tag": "0005_normal_brother_voodoo",
      "breakpoints": true
    },
    {
      "idx": 6,
      "version": "7",
      "when": 1727284647755,
      "tag": "0006_material_gargoyle",
      "breakpoints": true
    },
    {
      "idx": 7,
      "version": "7",
      "when": 1727286769885,
      "tag": "0007_certain_prism",
      "breakpoints": true
    },
    {
      "idx": 8,
      "version": "7",
      "when": 1727286851290,
      "tag": "0008_sour_riptide",
      "breakpoints": true
    },
    {
      "idx": 9,
      "version": "7",
      "when": 1727295044823,
      "tag": "0009_aspiring_killraven",
      "breakpoints": true
    }
  ]
}